voip_ms_moxad/__init__.py
voip_ms_moxad/blacklist.py
voip_ms_moxad/constants.py
voip_ms_moxad/functions.py
voip_ms_moxad/get_cdrs.py
voip_ms_moxad/get_did_info.py
voip_ms_moxad/globals.py
voip_ms_moxad/send_sms_message.py
voip_ms_moxad-0.8.5.dist-info/METADATA
voip_ms_moxad-0.8.5.dist-info/WHEEL
voip_ms_moxad-0.8.5.dist-info/entry_points.txt
voip_ms_moxad-0.8.5.dist-info/licenses/LICENSE.txt
voip_ms_moxad-0.8.5.dist-info/RECORD
