Metadata-Version: 2.4
Name: voip_ms_moxad
Version: 0.8.5
Summary: scripts using voip.ms API
Project-URL: Homepage, https://github.com/rjwhite/Python-voip.ms
Author-email: RJ White <rj.white@moxad.com>
License-File: LICENSE.txt
Classifier: Intended Audience :: End Users/Desktop
Classifier: License :: OSI Approved :: MIT License
Classifier: Natural Language :: English
Classifier: Operating System :: POSIX :: Linux
Classifier: Programming Language :: Python
Classifier: Programming Language :: Python :: 3
Requires-Dist: certifi>=2024.07.04
Requires-Dist: config-moxad>=4.0
Requires-Dist: idna>=3.7
Requires-Dist: requests>=2.32.4
Requires-Dist: urllib3>=2.5.0
